whats_that_code/__init__.py
whats_that_code/__main__.py
whats_that_code/_version.py
whats_that_code/codex_markers.py
whats_that_code/commands/__init__.py
whats_that_code/election.py
whats_that_code/extension_based.py
whats_that_code/guess_by_code_and_tags.py
whats_that_code/guess_by_popularity.py
whats_that_code/keyword_based.py
whats_that_code/known_languages.py
whats_that_code/parsing_based.py
whats_that_code/pygments_based.py
whats_that_code/regex_based.py
whats_that_code/shebang_based.py
whats_that_code/tag_based.py
whats_that_code/tags_data.py
whats_that_code-0.2.0.dist-info/LICENSE
whats_that_code-0.2.0.dist-info/METADATA
whats_that_code-0.2.0.dist-info/WHEEL
whats_that_code-0.2.0.dist-info/entry_points.txt
whats_that_code-0.2.0.dist-info/RECORD
