Metadata-Version: 2.1
Name: whats-that-code
Version: 0.2.0
Summary: Guess programming language from a string or file.
Home-page: https://github.com/matthewdeanmartin/whats_that_code
License: MIT
Keywords: language detection,programming language detection
Author: Matthew Martin
Author-email: matthewdeanmartin@gmail.com
Requires-Python: >=3.6,<4.0
Classifier: Development Status :: 4 - Beta
Classifier: Intended Audience :: Developers
Classifier: License :: OSI Approved :: MIT License
Classifier: Operating System :: OS Independent
Classifier: Programming Language :: Python
Classifier: Programming Language :: Python :: 3
Classifier: Programming Language :: Python :: 3.6
Classifier: Programming Language :: Python :: 3.7
Classifier: Programming Language :: Python :: 3.8
Classifier: Programming Language :: Python :: 3.9
Classifier: Programming Language :: Python :: 3.10
Classifier: Programming Language :: Python :: 3.11
Classifier: Programming Language :: Python :: 3.12
Requires-Dist: defusedxml
Requires-Dist: pygments
Requires-Dist: pyrankvote
Project-URL: Bug Tracker, https://github.com/matthewdeanmartin/whats_that_code/issues
Project-URL: Change Log, https://github.com/matthewdeanmartin/whats_that_code/blob/main/docs/CHANGES.md
Project-URL: Documentation, https://github.com/matthewdeanmartin/whats_that_code
Project-URL: Repository, https://github.com/matthewdeanmartin/whats_that_code
